./.gitignore
./PKG-INFO
./README.md
./main.py
./pyproject.toml
truffle_ai_image_editor_mcp-1.0.1.dist-info/METADATA
truffle_ai_image_editor_mcp-1.0.1.dist-info/WHEEL
truffle_ai_image_editor_mcp-1.0.1.dist-info/entry_points.txt
truffle_ai_image_editor_mcp-1.0.1.dist-info/RECORD
