Metadata-Version: 2.4
Name: truffle-ai-image-editor-mcp
Version: 1.0.1
Summary: MCP server for core image editing operations using OpenCV and Pillow
Author-email: Truffle AI <founders@trytruffle.ai>
Requires-Python: >=3.10
Requires-Dist: mcp>=1.0.0
Requires-Dist: numpy>=1.24.0
Requires-Dist: opencv-python>=4.8.0
Requires-Dist: pillow>=10.0.0
Requires-Dist: setuptools>=65.0.0
Provides-Extra: dev
Requires-Dist: black>=23.0.0; extra == 'dev'
Requires-Dist: pytest>=7.0.0; extra == 'dev'
Requires-Dist: ruff>=0.1.0; extra == 'dev'
